{
  "catalogue": "HM 33",
  "dimensions": {
    "height": "7.90",
    "length": "5.90",
    "source": "GORILA OCR",
    "thickness": "0.90",
    "unit": "cm"
  },
  "dimensionsRaw": "5,90 x 7,90 x 0,90 cm",
  "name": "HT24b",
  "tabulatedWords": ["ğ™ˆ", "ğ„‡", "ğ•", "ğ›‹ğ™ˆ", "ğ„‡", "ğ•", "ğ›’ğ™ˆ", "ğ„‡"],
  "tabulation": [
    [["ğ™ˆ", "", 0], ["ğ„‡", "", 1], ["ğ•", "", 2], ["ğ›‹", "", 3], ["ğ™ˆ", "", 3]],
    [["ğ„‡", "", 4], ["ğ•", "", 5], ["ğ›’", "", 6], ["ğ™ˆ", "", 6], ["ğ„‡", "", 7]]
  ]
}