{
  "catalogue": "HM20",
  "dimensions": {
    "height": "7.80",
    "length": "5.40",
    "source": "GORILA OCR",
    "thickness": "0.70",
    "unit": "cm"
  },
  "dimensionsRaw": "5,40 x 7,80 x 0,70 cm",
  "name": "HT32",
  "tabulatedWords": ["ğ™›", "ğ˜ğ˜½", "ğ„", "ğ™œ", "ğ†", "ğœ", "ğ†ğ‡", "ğš»", "ğ„‡", "ğ‡", "ğš¹", "ğ„‡", "ğ›š", "ğ„‡", "ğ˜²ğ˜™", "ğ„", "ğ„™ğ„", "ğ˜†", "ğ„•ğ„‹", "ğœ", "ğ˜™", "ğ„™ğ„Š", "ğ˜†", "ğ„”ğ„‰"],
  "tabulation": [
    [["ğ™›", "", 0], ["ğ˜", "", 1], ["ğ˜½", "", 1], ["ğ„", "", 2], ["ğ™œ", "", 3], ["ğ†", "", 4], ["ğœ", "", 5], ["ğ†", "", 6], ["ğ‡", "", 6]],
    [["ğš»", "", 7], ["ğ„‡", "", 8], ["ğ‡", "", 9], ["ğš¹", "", 10], ["ğ„‡", "", 11], ["ğ›š", "", 12], ["ğ„‡", "", 13]],
    [["ğ˜²", "", 14], ["ğ˜™", "", 14], ["ğ„", "", 15], ["ğ„™", "", 16], ["ğ„", "", 16], ["ğ˜†", "", 17], ["ğ„•", "", 18], ["ğ„‹", "", 18]],
    [["ğœ", "", 19], ["ğ˜™", "", 20], ["ğ„™", "", 21], ["ğ„Š", "", 21], ["ğ˜†", "", 22], ["ğ„”", "", 23], ["ğ„‰", "", 23]]
  ]
}