{
  "catalogue": "HM24",
  "dimensions": {
    "height": "7.80",
    "length": "5.80",
    "source": "GORILA OCR",
    "thickness": "0.60",
    "unit": "cm"
  },
  "dimensionsRaw": "5,80 x 7,80 x 0,60 cm",
  "name": "HT33",
  "tabulatedWords": ["ğ˜ğ˜½", "ğ„", "ğœ«", "ğšº", "ğ„‡", "ğƒ", "ğš¹", "ğ‰ğ‹", "ğ„‰", "ğ›†", "ğƒğ‰", "ğ›œ", "ğ‚", "ğ™™", "ğ„˜", "ğœ¦", "ğ„™", "ğ›", "ğ„™"],
  "tabulation": [
    [["ğ˜", "", 0], ["ğ˜½", "", 0], ["ğ„", "", 1], ["ğœ«", "", 2]],
    [["ğšº", "", 3], ["ğ„‡", "", 4], ["ğƒ", "", 5], ["ğš¹", "", 6], ["ğ‰", "", 7], ["ğ‹", "", 7]],
    [["ğ„‰", "", 8], ["ğ›†", "", 9], ["ğƒ", "", 10], ["ğ‰", "", 10], ["ğ›œ", "", 11], ["ğ‚", "", 12]],
    [["ğ™™", "", 13], ["ğ„˜", "", 14], ["ğœ¦", "", 15], ["ğ„™", "", 16], ["ğ›", "", 17], ["ğ„™", "", 18]]
  ]
}