{
  "catalogue": "",
  "dimensions": "",
  "dimensionsRaw": "",
  "name": "HT47a",
  "tabulatedWords": ["πΎ", "π›—", "π„", "π™‚π°π…πΉ", "π„‘", "π¬", "π„‘", "π‰", "πΆ", "π„", "πΈπ€π", "π„‹", "π»π―π»"],
  "tabulation": [
    [["πΎ", "", 0], ["π›—", "", 1], ["π„", "", 2], ["π™‚", "", 3], ["π°", "", 3]],
    [["π…", "", 3], ["πΉ", "", 3], ["π„‘", "", 4]],
    [["π¬", "", 5], ["π„‘", "", 6], ["π‰", "", 7], ["πΆ", "", 8]],
    [["π„", "", 9], ["πΈ", "", 10], ["π€", "", 10], ["π", "", 10], ["π„‹", "", 11]],
    [["π»", "", 12], ["π―", "", 12], ["π»", "", 12]]
  ]
}