{
  "catalogue": "",
  "dimensions": "",
  "dimensionsRaw": "",
  "name": "IOZa2",
  "tabulatedWords": ["π‡π³ππ™•π®π±", "π„", "π±π†πΈπΉ", "π„", "π±πππ΄π‹", "π„", "π‰π…πΎπ…π¤", "π„", "ππΆπ…π™", "π„", "π¤ππƒ", "π„", "π³π…π΄πƒπ‰π π―", "π„", "π", "π„"],
  "tabulation": [
    [["π‡", "", 0], ["π³", "", 0], ["π", "", 0], ["π™•", "", 0], ["π®", "", 0]],
    [["π±", "", 0], ["π„", "", 1], ["π±", "", 2], ["π†", "", 2], ["πΈ", "", 2], ["πΉ", "", 2], ["π„", "", 3], ["π±", "", 4]],
    [["π", "", 4], ["π", "", 4], ["π΄", "", 4], ["π‹", "", 4], ["π„", "", 5], ["π‰", "", 6], ["π…", "", 6]],
    [["πΎ", "", 6], ["π…", "", 6], ["π¤", "", 6], ["π„", "", 7], ["π", "", 8], ["πΆ", "", 8], ["π…", "", 8], ["π™", "", 8], ["π„", "", 9]],
    [["π¤", "", 10], ["π", "", 10], ["πƒ", "", 10], ["π„", "", 11], ["π³", "", 12], ["π…", "", 12], ["π΄", "", 12]],
    [["πƒ", "", 12], ["π‰", "", 12], ["π ", "", 12], ["π―", "", 12], ["π„", "", 13], ["π", "", 14], ["π„", "", 15]]
  ]
}